nanoballs/Shape_fitting.py
nanoballs/__init__.py
nanoballs/circle.py
nanoballs/contrast_adj.py
nanoballs/convert.py
nanoballs/imageseg.py
nanoballs/nanoballsfuncs.py
nanoballs/output.py
nanoballs/segmentparser.py
nanoballs/tests/__init__.py
nanoballs/tests/test_Shape_fitting.py
nanoballs/tests/test_circle.py
nanoballs/tests/test_convert.py
nanoballs/tests/test_imageseg.py
nanoballs-1.1.dist-info/LICENSE.txt
nanoballs-1.1.dist-info/METADATA
nanoballs-1.1.dist-info/WHEEL
nanoballs-1.1.dist-info/top_level.txt
nanoballs-1.1.dist-info/RECORD
