Metadata-Version: 2.1
Name: nanoballs
Version: 1.1
Summary: A package for SEM image and particle analysis
Home-page: https://github.com/rgebhart/nanoBALLS
Author: UNKNOWN
Author-email: UNKNOWN
License: UNKNOWN
Platform: UNKNOWN
